Metadata-Version: 2.1
Name: foxaysbasiccalculator
Version: 0.0.1
Summary: operation & greeting library
Author-email: foxay.tv@gmail.com
License-File: LICENCE.txt
